jikan_api_client/__init__.py
jikan_api_client/api/__init__.py
jikan_api_client/api/anime/__init__.py
jikan_api_client/api/anime/get_anime_by_id.py
jikan_api_client/api/anime/get_anime_characters.py
jikan_api_client/api/anime/get_anime_episode_by_id.py
jikan_api_client/api/anime/get_anime_episodes.py
jikan_api_client/api/anime/get_anime_external.py
jikan_api_client/api/anime/get_anime_forum.py
jikan_api_client/api/anime/get_anime_more_info.py
jikan_api_client/api/anime/get_anime_news.py
jikan_api_client/api/anime/get_anime_pictures.py
jikan_api_client/api/anime/get_anime_recommendations.py
jikan_api_client/api/anime/get_anime_relations.py
jikan_api_client/api/anime/get_anime_reviews.py
jikan_api_client/api/anime/get_anime_search.py
jikan_api_client/api/anime/get_anime_staff.py
jikan_api_client/api/anime/get_anime_statistics.py
jikan_api_client/api/anime/get_anime_themes.py
jikan_api_client/api/anime/get_anime_user_updates.py
jikan_api_client/api/anime/get_anime_videos.py
jikan_api_client/api/characters/__init__.py
jikan_api_client/api/characters/get_character_anime.py
jikan_api_client/api/characters/get_character_by_id.py
jikan_api_client/api/characters/get_character_manga.py
jikan_api_client/api/characters/get_character_pictures.py
jikan_api_client/api/characters/get_character_voice_actors.py
jikan_api_client/api/characters/get_characters_search.py
jikan_api_client/api/clubs/__init__.py
jikan_api_client/api/clubs/get_club_members.py
jikan_api_client/api/clubs/get_club_relations.py
jikan_api_client/api/clubs/get_club_staff.py
jikan_api_client/api/clubs/get_clubs_by_id.py
jikan_api_client/api/clubs/get_clubs_search.py
jikan_api_client/api/genres/__init__.py
jikan_api_client/api/genres/get_anime_genres.py
jikan_api_client/api/genres/get_manga_genres.py
jikan_api_client/api/magazines/__init__.py
jikan_api_client/api/magazines/get_magazines.py
jikan_api_client/api/manga/__init__.py
jikan_api_client/api/manga/get_manga_by_id.py
jikanpy_v4_alpha-0.0.1.dist-info/WHEEL
jikanpy_v4_alpha-0.0.1.dist-info/METADATA
jikanpy_v4_alpha-0.0.1.dist-info/RECORD
