Metadata-Version: 2.1
Name: jikanpy-v4-alpha
Version: 0.0.1
Summary: A client library for accessing Jikan API
Requires-Python: >=3.7,<4.0
Classifier: Programming Language :: Python :: 3
Classifier: Programming Language :: Python :: 3.10
Classifier: Programming Language :: Python :: 3.7
Classifier: Programming Language :: Python :: 3.8
Classifier: Programming Language :: Python :: 3.9
Provides-Extra: testing
Requires-Dist: attrs (>=21.3.0)
Requires-Dist: black (>=20.8b1); extra == "testing"
Requires-Dist: flake8 (>=4.0.0); extra == "testing"
Requires-Dist: httpx (>=0.15.4,<0.23.0)
Requires-Dist: mypy (>=0.782); extra == "testing"
Requires-Dist: pytest (>=5.4.2); extra == "testing"
Requires-Dist: python-dateutil (>=2.8.0,<3.0.0)
